Workbook
Name entry_multiple: Assumptions!$C$5
Name exit_multiple: Assumptions!$C$6
Name holding_period: Assumptions!$C$7
Name transaction_fees: Assumptions!$C$8
Name financing_fees: Assumptions!$C$9
Name mgmt_rollover: Assumptions!$C$10
Name senior_multiple: Assumptions!$C$14
Name senior_rate: Assumptions!$C$15
Name senior_amort: Assumptions!$C$16
Name mezz_multiple: Assumptions!$C$17
Name mezz_rate: Assumptions!$C$18
Name mezz_pik: Assumptions!$C$19
Name sub_multiple: Assumptions!$C$20
Name sub_rate: Assumptions!$C$21
Name rev_growth: Assumptions!$C$25
Name ebitda_margin: Assumptions!$C$26
Name da_pct: Assumptions!$C$27
Name capex_pct: Assumptions!$C$28
Name nwc_pct: Assumptions!$C$29
Name tax_rate: Assumptions!$C$30
Name total_uses: Sources_Uses!$C$9
Name sponsor_equity: Sources_Uses!$C$17
Name op_ebitda_row: Operating!$B$9
Name op_revenue_row: Operating!$B$6

Sheet Cover
A1: NTPC - LBO Analysis
B4: Company | C4: NTPC
B5: Industry | C5: General
B6: Analysis Date | C6: January 30, 2026
B7: Holding Period | C7: 5 Years
B8: Entry Multiple | C8: 8.0x EV/EBITDA
B9: Exit Multiple | C9: 8.0x EV/EBITDA
B12: Model Contents
C13: • Assumptions - Transaction & Operating Assumptions
C14: • Sources & Uses - Transaction Funding Structure
C15: • Operating Model - Revenue & EBITDA Projections
C16: • Debt Schedule - Senior, Mezz, Subordinated Tranches
C17: • Cash Flow - Free Cash Flow & Debt Paydown
C18: • Returns - IRR, MoIC, Payback Analysis
C19: • Sensitivity - Returns by Exit Multiple & Leverage

Sheet Assumptions
A1: LBO Assumptions
B4: Transaction Assumptions
B5: Entry EV/EBITDA Multiple | C5: 8
B6: Exit EV/EBITDA Multiple | C6: 8
B7: Holding Period (Years) | C7: 5
B8: Transaction Fees (% of EV) | C8: 0.02
B9: Financing Fees (% of Debt) | C9: 0.03
B10: Management Rollover (%) | C10: 0.1
B13: Debt Structure
B14: Senior Debt Multiple (x EBITDA) | C14: 3
B15: Senior Interest Rate | C15: 0.08
B16: Senior Amortization (Years) | C16: 7
B17: Mezzanine Debt Multiple (x EBITDA) | C17: 1.5
B18: Mezzanine Cash Interest | C18: 0.12
B19: Mezzanine PIK Interest | C19: 0.02
B20: Subordinated Debt Multiple (x EBITDA) | C20: 0.5
B21: Subordinated Interest Rate | C21: 0.14
B24: Operating Assumptions
B25: Revenue Growth Rate | C25: 0.08
B26: EBITDA Margin | C26: 0.25
B27: D&A (% of Revenue) | C27: 0.05
B28: CapEx (% of Revenue) | C28: 0.04
B29: Working Capital (% of Revenue) | C29: 0.1
B30: Tax Rate | C30: 0.25

Sheet Sources_Uses
A1: Sources & Uses of Funds
B4: Uses of Funds | C4: Amount | D4: % of Total
B5: Purchase Enterprise Value | C5: =1000*entry_multiple | D5: =C5/C9
B6: Transaction Fees | C6: =B5*transaction_fees | D6: =C6/C9
B7: Financing Fees | C7: =(senior_multiple+mezz_multiple+sub_multiple)*1000*financing_fees | D7: =C7/C9
B8: Minimum Cash | C8: 50 | D8: =C8/C9
B9: Total Uses | C9: =SUM(C5:C8)
B12: Sources of Funds | C12: Amount | D12: % of Total | E12: x EBITDA
B13: Senior Debt | C13: =senior_multiple*1000 | D13: =C13/C18 | E13: =C13/1000
B14: Mezzanine Debt | C14: =mezz_multiple*1000 | D14: =C14/C18 | E14: =C14/1000
B15: Subordinated Debt | C15: =sub_multiple*1000 | D15: =C15/C18 | E15: =C15/1000
B16: Management Rollover | C16: =(C9-C13-C14-C15)*mgmt_rollover | D16: =C16/C18 | E16: =C16/1000
B17: Sponsor Equity (Plug) | C17: =C9-SUM(C13:C16) | D17: =C17/C18 | E17: =C17/1000
B18: Total Sources | C18: =SUM(C13:C17)
B20: Sources - Uses Check | C20: =C18-C9

Sheet Operating
A1: Operating Model
B4: Fiscal Year | C4: Entry | D4: Year 1 | E4: Year 2 | F4: Year 3 | G4: Year 4 | H4: Year 5
B6: Revenue | C6: 5000 | D6: =C6*(1+rev_growth) | E6: =D6*(1+rev_growth) | F6: =E6*(1+rev_growth) | G6: =F6*(1+rev_growth) | H6: =G6*(1+rev_growth)
B7: % Growth | C7: - | D7: =D6/C6-1 | E7: =E6/D6-1 | F7: =F6/E6-1 | G7: =G6/F6-1 | H7: =H6/G6-1
B9: EBITDA | C9: =C6*ebitda_margin | D9: =D6*ebitda_margin | E9: =E6*ebitda_margin | F9: =F6*ebitda_margin | G9: =G6*ebitda_margin | H9: =H6*ebitda_margin
B10: % Margin | C10: =C9/C6 | D10: =D9/D6 | E10: =E9/E6 | F10: =F9/F6 | G10: =G9/G6 | H10: =H9/H6
B12: Depreciation & Amortization | C12: =C6*da_pct | D12: =D6*da_pct | E12: =E6*da_pct | F12: =F6*da_pct | G12: =G6*da_pct | H12: =H6*da_pct
B13: EBIT | C13: =C9-C12 | D13: =D9-D12 | E13: =E9-E12 | F13: =F9-F12 | G13: =G9-G12 | H13: =H9-H12
B15: Interest Expense | C15: =IF(ISERROR(Debt_Schedule!C$50),0,Debt_Schedule!C$50) | D15: =IF(ISERROR(Debt_Schedule!D$50),0,Debt_Schedule!D$50) | E15: =IF(ISERROR(Debt_Schedule!E$50),0,Debt_Schedule!E$50) | F15: =IF(ISERROR(Debt_Schedule!F$50),0,Debt_Schedule!F$50) | G15: =IF(ISERROR(Debt_Schedule!G$50),0,Debt_Schedule!G$50) | H15: =IF(ISERROR(Debt_Schedule!H$50),0,Debt_Schedule!H$50)
B16: EBT (Earnings Before Tax) | C16: =C13-C15 | D16: =D13-D15 | E16: =E13-E15 | F16: =F13-F15 | G16: =G13-G15 | H16: =H13-H15
B17: Taxes | C17: =MAX(0,C16*tax_rate) | D17: =MAX(0,D16*tax_rate) | E17: =MAX(0,E16*tax_rate) | F17: =MAX(0,F16*tax_rate) | G17: =MAX(0,G16*tax_rate) | H17: =MAX(0,H16*tax_rate)
B18: Net Income | C18: =C16-C17 | D18: =D16-D17 | E18: =E16-E17 | F18: =F16-F17 | G18: =G16-G17 | H18: =H16-H17

Sheet Debt_Schedule
A1: Debt Schedule
B4: Fiscal Year | C4: Entry | D4: Year 1 | E4: Year 2 | F4: Year 3 | G4: Year 4 | H4: Year 5
B6: Senior Debt
B7: Beginning Balance | C7: =senior_multiple*1000 | D7: =C10 | E7: =D10 | F7: =E10 | G7: =F10 | H7: =G10
B8: Mandatory Amortization | C8: 0 | D8: =-C7/senior_amort | E8: =-C7/senior_amort | F8: =-C7/senior_amort | G8: =-C7/senior_amort | H8: =-C7/senior_amort
B9: Optional Prepayment | C9: 0 | D9: =-MIN(D7+D8,MAX(0,Cash_Flow!D$40)) | E9: =-MIN(E7+E8,MAX(0,Cash_Flow!E$40)) | F9: =-MIN(F7+F8,MAX(0,Cash_Flow!F$40)) | G9: =-MIN(G7+G8,MAX(0,Cash_Flow!G$40)) | H9: =-MIN(H7+H8,MAX(0,Cash_Flow!H$40))
B10: Ending Balance | C10: =MAX(0,C7+C8+C9) | D10: =MAX(0,D7+D8+D9) | E10: =MAX(0,E7+E8+E9) | F10: =MAX(0,F7+F8+F9) | G10: =MAX(0,G7+G8+G9) | H10: =MAX(0,H7+H8+H9)
B11: Interest Expense | C11: =C7*senior_rate | D11: =D7*senior_rate | E11: =E7*senior_rate | F11: =F7*senior_rate | G11: =G7*senior_rate | H11: =H7*senior_rate
B14: Mezzanine Debt
B15: Beginning Balance | C15: =mezz_multiple*1000 | D15: =C17 | E15: =D17 | F15: =E17 | G15: =F17 | H15: =G17
B16: PIK Interest | C16: =C15*mezz_pik | D16: =D15*mezz_pik | E16: =E15*mezz_pik | F16: =F15*mezz_pik | G16: =G15*mezz_pik | H16: =H15*mezz_pik
B17: Ending Balance | C17: =C15+C16 | D17: =D15+D16 | E17: =E15+E16 | F17: =F15+F16 | G17: =G15+G16 | H17: =H15+H16
B18: Cash Interest | C18: =C15*mezz_rate | D18: =D15*mezz_rate | E18: =E15*mezz_rate | F18: =F15*mezz_rate | G18: =G15*mezz_rate | H18: =H15*mezz_rate
B21: Subordinated Debt
B22: Beginning Balance | C22: =sub_multiple*1000 | D22: =C23 | E22: =D23 | F22: =E23 | G22: =F23 | H22: =G23
B23: Ending Balance | C23: =C22 | D23: =D22 | E23: =E22 | F23: =F22 | G23: =G22 | H23: =H22
B24: Interest Expense | C24: =C22*sub_rate | D24: =D22*sub_rate | E24: =E22*sub_rate | F24: =F22*sub_rate | G24: =G22*sub_rate | H24: =H22*sub_rate
B27: Total Debt Summary
B28: Total Debt | C28: =C10+C17+C23 | D28: =D10+D17+D23 | E28: =E10+E17+E23 | F28: =F10+F17+F23 | G28: =G10+G17+G23 | H28: =H10+H17+H23
B50: Total Interest Expense | C50: =C11+C18+C24 | D50: =D11+D18+D24 | E50: =E11+E18+E24 | F50: =F11+F18+F24 | G50: =G11+G18+G24 | H50: =H11+H18+H24

Sheet Cash_Flow
A1: Cash Flow Statement
B4: Fiscal Year | C4: Entry | D4: Year 1 | E4: Year 2 | F4: Year 3 | G4: Year 4 | H4: Year 5
B6: EBITDA | C6: =Operating!C$10 | D6: =Operating!D$10 | E6: =Operating!E$10 | F6: =Operating!F$10 | G6: =Operating!G$10 | H6: =Operating!H$10
B7: Less: Cash Interest | C7: =-Debt_Schedule!C$50 | D7: =-Debt_Schedule!D$50 | E7: =-Debt_Schedule!E$50 | F7: =-Debt_Schedule!F$50 | G7: =-Debt_Schedule!G$50 | H7: =-Debt_Schedule!H$50
B8: Less: Cash Taxes | C8: =-MAX(0,(C6+C7)*tax_rate) | D8: =-MAX(0,(D6+D7)*tax_rate) | E8: =-MAX(0,(E6+E7)*tax_rate) | F8: =-MAX(0,(F6+F7)*tax_rate) | G8: =-MAX(0,(G6+G7)*tax_rate) | H8: =-MAX(0,(H6+H7)*tax_rate)
B9: Less: CapEx | C9: =-Operating!C$6*capex_pct | D9: =-Operating!D$6*capex_pct | E9: =-Operating!E$6*capex_pct | F9: =-Operating!F$6*capex_pct | G9: =-Operating!G$6*capex_pct | H9: =-Operating!H$6*capex_pct
B10: Less: Change in NWC | C10: 0 | D10: =-(Operating!D$6-Operating!C$6)*nwc_pct | E10: =-(Operating!E$6-Operating!D$6)*nwc_pct | F10: =-(Operating!F$6-Operating!E$6)*nwc_pct | G10: =-(Operating!G$6-Operating!F$6)*nwc_pct | H10: =-(Operating!H$6-Operating!G$6)*nwc_pct
B12: Free Cash Flow | C12: =SUM(C6:C10) | D12: =SUM(D6:D10) | E12: =SUM(E6:E10) | F12: =SUM(F6:F10) | G12: =SUM(G6:G10) | H12: =SUM(H6:H10)
B14: Less: Mandatory Debt Amortization | C14: =Debt_Schedule!C$8 | D14: =Debt_Schedule!D$8 | E14: =Debt_Schedule!E$8 | F14: =Debt_Schedule!F$8 | G14: =Debt_Schedule!G$8 | H14: =Debt_Schedule!H$8
B40: Cash Available for Sweep | C40: =C12+C14 | D40: =D12+D14 | E40: =E12+E14 | F40: =F12+F14 | G40: =G12+G14 | H40: =H12+H14

Sheet Returns
A1: Returns Analysis
B4: Exit Analysis
B5: Exit Year EBITDA | C5: =Operating!H$10
B6: Exit EV/EBITDA Multiple | C6: =exit_multiple
B7: Exit Enterprise Value | C7: =C5*exit_multiple
B8: Less: Debt at Exit | C8: =-Debt_Schedule!H$45
B9: Exit Equity Value | C9: =C7+C8
B12: Returns Summary
B13: Initial Sponsor Equity | C13: =sponsor_equity
B14: Exit Equity Proceeds | C14: =C9
B16: Multiple on Invested Capital (MoIC) | C16: =C9/C13
B17: Internal Rate of Return (IRR) | C17: =IRR({-C13,0,0,0,0,C9})
B18: Payback Period (Years) | C18: =holding_period/LN(C16)*LN(2)
B21: Cash-on-Cash Return by Exit Year
B22: Exit Year | C22: MoIC | D22: IRR
B23: Year 1 | C23: =(Operating!D$10*exit_multiple-Debt_Schedule!D$45)/sponsor_equity | D23: =C23^(1/1)-1
B24: Year 2 | C24: =(Operating!E$10*exit_multiple-Debt_Schedule!E$45)/sponsor_equity | D24: =C24^(1/2)-1
B25: Year 3 | C25: =(Operating!F$10*exit_multiple-Debt_Schedule!F$45)/sponsor_equity | D25: =C25^(1/3)-1
B26: Year 4 | C26: =(Operating!G$10*exit_multiple-Debt_Schedule!G$45)/sponsor_equity | D26: =C26^(1/4)-1
B27: Year 5 | C27: =(Operating!H$10*exit_multiple-Debt_Schedule!H$45)/sponsor_equity | D27: =C27^(1/5)-1

Sheet Sensitivity
A1: Sensitivity Analysis
B4: IRR Sensitivity: Exit Multiple vs Entry Multiple
B6: IRR | C6: 6.0x | D6: 7.0x | E6: 8.0x | F6: 9.0x | G6: 10.0x | H6: 11.0x
B7: 6.0x Entry | C7: =(((6.0*1000*(1+rev_growth)^5)/((6.0*1000)*0.4))^(1/5)-1) | D7: =(((7.0*1000*(1+rev_growth)^5)/((6.0*1000)*0.4))^(1/5)-1) | E7: =(((8.0*1000*(1+rev_growth)^5)/((6.0*1000)*0.4))^(1/5)-1) | F7: =(((9.0*1000*(1+rev_growth)^5)/((6.0*1000)*0.4))^(1/5)-1) | G7: =(((10.0*1000*(1+rev_growth)^5)/((6.0*1000)*0.4))^(1/5)-1) | H7: =(((11.0*1000*(1+rev_growth)^5)/((6.0*1000)*0.4))^(1/5)-1)
B8: 7.0x Entry | C8: =(((6.0*1000*(1+rev_growth)^5)/((7.0*1000)*0.4))^(1/5)-1) | D8: =(((7.0*1000*(1+rev_growth)^5)/((7.0*1000)*0.4))^(1/5)-1) | E8: =(((8.0*1000*(1+rev_growth)^5)/((7.0*1000)*0.4))^(1/5)-1) | F8: =(((9.0*1000*(1+rev_growth)^5)/((7.0*1000)*0.4))^(1/5)-1) | G8: =(((10.0*1000*(1+rev_growth)^5)/((7.0*1000)*0.4))^(1/5)-1) | H8: =(((11.0*1000*(1+rev_growth)^5)/((7.0*1000)*0.4))^(1/5)-1)
B9: 8.0x Entry | C9: =(((6.0*1000*(1+rev_growth)^5)/((8.0*1000)*0.4))^(1/5)-1) | D9: =(((7.0*1000*(1+rev_growth)^5)/((8.0*1000)*0.4))^(1/5)-1) | E9: =(((8.0*1000*(1+rev_growth)^5)/((8.0*1000)*0.4))^(1/5)-1) | F9: =(((9.0*1000*(1+rev_growth)^5)/((8.0*1000)*0.4))^(1/5)-1) | G9: =(((10.0*1000*(1+rev_growth)^5)/((8.0*1000)*0.4))^(1/5)-1) | H9: =(((11.0*1000*(1+rev_growth)^5)/((8.0*1000)*0.4))^(1/5)-1)
B10: 9.0x Entry | C10: =(((6.0*1000*(1+rev_growth)^5)/((9.0*1000)*0.4))^(1/5)-1) | D10: =(((7.0*1000*(1+rev_growth)^5)/((9.0*1000)*0.4))^(1/5)-1) | E10: =(((8.0*1000*(1+rev_growth)^5)/((9.0*1000)*0.4))^(1/5)-1) | F10: =(((9.0*1000*(1+rev_growth)^5)/((9.0*1000)*0.4))^(1/5)-1) | G10: =(((10.0*1000*(1+rev_growth)^5)/((9.0*1000)*0.4))^(1/5)-1) | H10: =(((11.0*1000*(1+rev_growth)^5)/((9.0*1000)*0.4))^(1/5)-1)
B11: 10.0x Entry | C11: =(((6.0*1000*(1+rev_growth)^5)/((10.0*1000)*0.4))^(1/5)-1) | D11: =(((7.0*1000*(1+rev_growth)^5)/((10.0*1000)*0.4))^(1/5)-1) | E11: =(((8.0*1000*(1+rev_growth)^5)/((10.0*1000)*0.4))^(1/5)-1) | F11: =(((9.0*1000*(1+rev_growth)^5)/((10.0*1000)*0.4))^(1/5)-1) | G11: =(((10.0*1000*(1+rev_growth)^5)/((10.0*1000)*0.4))^(1/5)-1) | H11: =(((11.0*1000*(1+rev_growth)^5)/((10.0*1000)*0.4))^(1/5)-1)
B15: MoIC Sensitivity: Exit Multiple vs Leverage
B17: MoIC | C17: 6.0x Exit | D17: 7.0x Exit | E17: 8.0x Exit | F17: 9.0x Exit | G17: 10.0x Exit | H17: 11.0x Exit
B18: 3.0x Leverage | C18: =(8815.968460800003-3000.0*0.7)/5000.0 | D18: =(10285.296537600005-3000.0*0.7)/5000.0 | E18: =(11754.624614400005-3000.0*0.7)/5000.0 | F18: =(13223.952691200006-3000.0*0.7)/5000.0 | G18: =(14693.280768000006-3000.0*0.7)/5000.0 | H18: =(16162.608844800006-3000.0*0.7)/5000.0
B19: 4.0x Leverage | C19: =(8815.968460800003-4000.0*0.7)/4000.0 | D19: =(10285.296537600005-4000.0*0.7)/4000.0 | E19: =(11754.624614400005-4000.0*0.7)/4000.0 | F19: =(13223.952691200006-4000.0*0.7)/4000.0 | G19: =(14693.280768000006-4000.0*0.7)/4000.0 | H19: =(16162.608844800006-4000.0*0.7)/4000.0
B20: 5.0x Leverage | C20: =(8815.968460800003-5000.0*0.7)/3000.0 | D20: =(10285.296537600005-5000.0*0.7)/3000.0 | E20: =(11754.624614400005-5000.0*0.7)/3000.0 | F20: =(13223.952691200006-5000.0*0.7)/3000.0 | G20: =(14693.280768000006-5000.0*0.7)/3000.0 | H20: =(16162.608844800006-5000.0*0.7)/3000.0
B21: 6.0x Leverage | C21: =(8815.968460800003-6000.0*0.7)/2000.0 | D21: =(10285.296537600005-6000.0*0.7)/2000.0 | E21: =(11754.624614400005-6000.0*0.7)/2000.0 | F21: =(13223.952691200006-6000.0*0.7)/2000.0 | G21: =(14693.280768000006-6000.0*0.7)/2000.0 | H21: =(16162.608844800006-6000.0*0.7)/2000.0
