Workbook
Name Revenue_Growth_Rate: 'Assumptions'!$C$7
Name Capex_pct_of_Revenue: 'Assumptions'!$C$24
Name Terminal_Growth: 'Assumptions'!$C$33
Name Gross_Margin: 'Assumptions'!$C$13
Name EBITDA_Margin: 'Assumptions'!$C$14
Name Cost_of_Debt: 'Assumptions'!$C$32
Name Working_Capital_Days: 'Assumptions'!$C$19
Name D&A_pct_of_Gross_PPE: 'Assumptions'!$C$23
Name Tax_Rate: 'Assumptions'!$C$28
Name Risk-free_Rate: 'Assumptions'!$C$29
Name Equity_Risk_Premium: 'Assumptions'!$C$30
Name Beta: 'Assumptions'!$C$31

Sheet Cover
B2: ADANIPOWER
B3: Financial Model
B4: Model Date: 29-Jan-2026
B7: Company Information | E7: Model Navigation
B8: Industry | C8: Power & Utilities | E8: Cover
B9: Sub-sector | E9: Assumptions
B10: Model Type | C10: Power Sector | E10: Historical
E11: Forecast_IS
E12: Forecast_BS
B13: Key Metrics | E13: Forecast_CF
B14: Current Price | C14: N/A | E14: Working_Capital
B15: Market Cap | C15: N/A | E15: Debt_Schedule
B16: P/E Ratio | C16: N/A | E16: Valuation
B17: Revenue (LTM) | C17: N/A | E17: Dashboard
B18: EBITDA (LTM) | C18: N/A
B19: ROE | C19: N/A
B22: Valuation Summary
B23: DCF Equity Value | C23: =Valuation!$G$25
B24: Implied Share Price | C24: =Valuation!$G$28
B25: Current Price
B26: Upside / Downside | C26: =IFERROR((Valuation!$G$28/C25)-1, 0)

Sheet Assumptions
B2: Model Assumptions
B3: Yellow cells are inputs - modify these to update the model
B5: Growth & Revenue
B6: Assumption | C6: Value | D6: Unit | E6: Driver Logic
B7: Revenue Growth Rate | C7: 0.1 | D7: percent | E7: Industry growth + market share gains
B8: Capex % of Revenue | C8: 0.05 | D8: percent | E8: Maintenance + growth capex
B9: Terminal Growth | C9: 0.04 | D9: percent | E9: Long-term GDP growth
B11: Margins & Costs
B12: Assumption | C12: Value | D12: Unit | E12: Driver Logic
B13: Gross Margin | C13: 0.4 | D13: percent | E13: Historical average with efficiency improvements
B14: EBITDA Margin | C14: 0.2 | D14: percent | E14: Operating leverage and cost optimization
B15: Cost of Debt | C15: 0.1 | D15: percent | E15: Current borrowing rate
B17: Working Capital
B18: Assumption | C18: Value | D18: Unit | E18: Driver Logic
B19: Working Capital Days | C19: 45 | D19: days | E19: Industry benchmark
B21: Capital Structure
B22: Assumption | C22: Value | D22: Unit | E22: Driver Logic
B23: D&A % of Gross PPE | C23: 0.05 | D23: percent | E23: Based on asset life
B24: Capex % of Revenue | C24: 0.05 | D24: percent | E24: Maintenance + growth capex
B26: Valuation
B27: Assumption | C27: Value | D27: Unit | E27: Driver Logic
B28: Tax Rate | C28: 0.25 | D28: percent | E28: Statutory rate
B29: Risk-free Rate | C29: 0.07 | D29: percent | E29: 10-year G-Sec yield
B30: Equity Risk Premium | C30: 0.06 | D30: percent | E30: India market risk premium
B31: Beta | C31: 1 | D31: number | E31: Industry average
B32: Cost of Debt | C32: 0.1 | D32: percent | E32: Current borrowing rate
B33: Terminal Growth | C33: 0.04 | D33: percent | E33: Long-term GDP growth

Sheet Historical
B2: Historical Financials
B4: ₹ in Crores | C4: FY2021 | D4: FY2022 | E4: FY2023 | F4: FY2024 | G4: FY2025
B6: Income Statement
B7: Revenue
B8: Cost of Goods Sold
B9: Gross Profit
B10: Operating Expenses
B11: EBITDA
B12: Depreciation & Amortization
B13: EBIT
B14: Interest Expense
B15: Pre-tax Income
B16: Tax Expense
B17: Net Income
... B40: Dividends Paid

Sheet Power_Operations
B2: Power Operations
C4: FY2025 | D4: FY2026E | E4: FY2027E | F4: FY2028E | G4: FY2029E | H4: FY2030E
B6: CAPACITY
B7: Installed Capacity (MW) | D7: =C7 | E7: =D7 | F7: =E7 | G7: =F7 | H7: =G7
B8: Operational Capacity (MW) | D8: =C7*0.95 | E8: =D7*0.95 | F8: =E7*0.95 | G8: =F7*0.95 | H8: =G7*0.95
B10: GENERATION
B11: Plant Load Factor (%) | D11: =PLF | E11: =PLF | F11: =PLF | G11: =PLF | H11: =PLF
B12: Availability Factor (%) | D12: =0.90 | E12: =0.90 | F12: =0.90 | G12: =0.90 | H12: =0.90
B13: Hours in Year | D13: =8760 | E13: =8760 | F13: =8760 | G13: =8760 | H13: =8760
B14: Units Generated (MU) | D14: =C8*C11*C13/1000 | E14: =D8*D11*D13/1000 | F14: =E8*E11*E13/1000 | G14: =F8*F11*F13/1000 | H14: =G8*G11*G13/1000
B16: REVENUE
B17: Tariff per kWh (₹) | D17: =Tariff_per_kWh | E17: =Tariff_per_kWh | F17: =Tariff_per_kWh | G17: =Tariff_per_kWh | H17: =Tariff_per_kWh
B18: Capacity Charges | D18: =C8*C16*0.4*1000 | E18: =D8*D16*0.4*1000 | F18: =E8*E16*0.4*1000 | G18: =F8*F16*0.4*1000 | H18: =G8*G16*0.4*1000
B19: Energy Charges | D19: =C14*C16*10 | E19: =D14*D16*10 | F19: =E14*E16*10 | G19: =F14*F16*10 | H19: =G14*G16*10
B20: Total Revenue | D20: =C17+C18 | E20: =D17+D18 | F20: =E17+E18 | G20: =F17+F18 | H20: =G17+G18
B22: FUEL & COSTS
B23: Heat Rate (kcal/kWh) | D23: =2500 | E23: =2500 | F23: =2500 | G23: =2500 | H23: =2500
B24: Coal Price (₹/ton) | D24: =5000 | E24: =5000 | F24: =5000 | G24: =5000 | H24: =5000
B25: Coal Consumption (tons) | D25: =C14*C21*1000000/5000000 | E25: =D14*D21*1000000/5000000 | F25: =E14*E21*1000000/5000000 | G25: =F14*F21*1000000/5000000 | H25: =G14*G21*1000000/5000000
B26: Fuel Cost | D26: =C23*C22 | E26: =D23*D22 | F26: =E23*E22 | G26: =F23*F22 | H26: =G23*G22
B27: Other O&M | D27: =C19*0.10 | E27: =D19*0.10 | F27: =E19*0.10 | G27: =F19*0.10 | H27: =G19*0.10
B28: EBITDA | D28: =C19-C24-C25 | E28: =D19-D24-D25 | F28: =E19-E24-E25 | G28: =F19-F24-F25 | H28: =G19-G24-G25
B30: PROJECT FINANCE
B31: Cash Flow for Debt Service | D31: =C26+Forecast_IS!C15 | E31: =D26+Forecast_IS!D15 | F31: =E26+Forecast_IS!E15 | G31: =F26+Forecast_IS!F15 | H31: =G26+Forecast_IS!G15
B32: Debt Service | D32: =Debt_Schedule!C22+Debt_Schedule!C13 | E32: =Debt_Schedule!D22+Debt_Schedule!D13 | F32: =Debt_Schedule!E22+Debt_Schedule!E13 | G32: =Debt_Schedule!F22+Debt_Schedule!F13 | H32: =Debt_Schedule!G22+Debt_Schedule!G13
B33: DSCR | D33: =IFERROR(C28/C29,0) | E33: =IFERROR(D28/D29,0) | F33: =IFERROR(E28/E29,0) | G33: =IFERROR(F28/F29,0) | H33: =IFERROR(G28/G29,0)

Sheet Forecast_IS
B2: Forecast Income Statement
B4: ₹ in Crores | C4: FY2025 | D4: FY2026E | E4: FY2027E | F4: FY2028E | G4: FY2029E | H4: FY2030E
B6: Revenue | D6: =C6*(1+Revenue_Growth_Rate) | E6: =D6*(1+Revenue_Growth_Rate) | F6: =E6*(1+Revenue_Growth_Rate) | G6: =F6*(1+Revenue_Growth_Rate) | H6: =G6*(1+Revenue_Growth_Rate)
B8: Cost of Goods Sold | D8: =-C6*(1-Gross_Margin) | E8: =-D6*(1-Gross_Margin) | F8: =-E6*(1-Gross_Margin) | G8: =-F6*(1-Gross_Margin) | H8: =-G6*(1-Gross_Margin)
B9: Gross Profit | D9: =C6+C8 | E9: =D6+D8 | F9: =E6+E8 | G9: =F6+F8 | H9: =G6+G8
B11: Operating Expenses | D11: =-C6*0.15 | E11: =-D6*0.15 | F11: =-E6*0.15 | G11: =-F6*0.15 | H11: =-G6*0.15
B12: EBITDA | D12: =C9+C11 | E12: =D9+D11 | F12: =E9+E11 | G12: =F9+F11 | H12: =G9+G11
B13: EBITDA Margin | D13: =IFERROR(C12/C6,0) | E13: =IFERROR(D12/D6,0) | F13: =IFERROR(E12/E6,0) | G13: =IFERROR(F12/F6,0) | H13: =IFERROR(G12/G6,0)
B15: Depreciation & Amortization | D15: =-Forecast_BS!C15*0.05 | E15: =-Forecast_BS!D15*0.05 | F15: =-Forecast_BS!E15*0.05 | G15: =-Forecast_BS!F15*0.05 | H15: =-Forecast_BS!G15*0.05
B16: EBIT | D16: =C12+C15 | E16: =D12+D15 | F16: =E12+E15 | G16: =F12+F15 | H16: =G12+G15
B17: EBIT Margin | D17: =IFERROR(C16/C6,0) | E17: =IFERROR(D16/D6,0) | F17: =IFERROR(E16/E6,0) | G17: =IFERROR(F16/F6,0) | H17: =IFERROR(G16/G6,0)
B19: Interest Expense | D19: =-Debt_Schedule!C15*Cost_of_Debt | E19: =-Debt_Schedule!D15*Dost_of_Debt | F19: =-Debt_Schedule!E15*Eost_of_Debt | G19: =-Debt_Schedule!F15*Fost_of_Debt | H19: =-Debt_Schedule!G15*Gost_of_Debt
B20: Interest Income | D20: =Forecast_BS!C6*0.04 | E20: =Forecast_BS!D6*0.04 | F20: =Forecast_BS!E6*0.04 | G20: =Forecast_BS!F6*0.04 | H20: =Forecast_BS!G6*0.04
B21: Pre-tax Income | D21: =C16+C19+C20 | E21: =D16+D19+D20 | F21: =E16+E19+E20 | G21: =F16+F19+F20 | H21: =G16+G19+G20
B23: Tax Expense | D23: =-MAX(C21,0)*Tax_Rate | E23: =-MAX(D21,0)*Tax_Rate | F23: =-MAX(E21,0)*Tax_Rate | G23: =-MAX(F21,0)*Tax_Rate | H23: =-MAX(G21,0)*Tax_Rate
B24: Net Income | D24: =C21+C23 | E24: =D21+D23 | F24: =E21+E23 | G24: =F21+F23 | H24: =G21+G23
B25: Net Margin | D25: =IFERROR(C24/C6,0) | E25: =IFERROR(D24/D6,0) | F25: =IFERROR(E24/E6,0) | G25: =IFERROR(F24/F6,0) | H25: =IFERROR(G24/G6,0)

Sheet Forecast_BS
B2: Forecast Balance Sheet
B4: ₹ in Crores | C4: FY2025 | D4: FY2026E | E4: FY2027E | F4: FY2028E | G4: FY2029E | H4: FY2030E
B6: ASSETS
B7: Cash & Equivalents | D7: =C6+Forecast_CF!C28 | E7: =D6+Forecast_DF!D28 | F7: =E6+Forecast_EF!E28 | G7: =F6+Forecast_FF!F28 | H7: =G6+Forecast_GF!G28
B8: Trade Receivables | D8: =Forecast_IS!C6*Receivable_Days/365 | E8: =Forecast_IS!D6*Receivable_Days/365 | F8: =Forecast_IS!E6*Receivable_Days/365 | G8: =Forecast_IS!F6*Receivable_Days/365 | H8: =Forecast_IS!G6*Receivable_Days/365
B9: Inventory | D9: =-Forecast_IS!C8*Inventory_Days/365 | E9: =-Forecast_IS!D8*Inventory_Days/365 | F9: =-Forecast_IS!E8*Inventory_Days/365 | G9: =-Forecast_IS!F8*Inventory_Days/365 | H9: =-Forecast_IS!G8*Inventory_Days/365
B10: Other Current Assets | D10: =C10*1.02 | E10: =D10*1.02 | F10: =E10*1.02 | G10: =F10*1.02 | H10: =G10*1.02
B11: Total Current Assets | D11: =SUM(C7:C10) | E11: =SUM(D7:D10) | F11: =SUM(E7:E10) | G11: =SUM(F7:F10) | H11: =SUM(G7:G10)
B13: Gross PP&E | D13: =C13-Forecast_IS!C15+Forecast_CF!C18 | E13: =D13-Forecast_IS!D15+Forecast_DF!D18 | F13: =E13-Forecast_IS!E15+Forecast_EF!E18 | G13: =F13-Forecast_IS!F15+Forecast_FF!F18 | H13: =G13-Forecast_IS!G15+Forecast_GF!G18
B14: Accumulated Depreciation | D14: =C14+Forecast_IS!C15 | E14: =D14+Forecast_IS!D15 | F14: =E14+Forecast_IS!E15 | G14: =F14+Forecast_IS!F15 | H14: =G14+Forecast_IS!G15
B15: Net PP&E | D15: =C13+C14 | E15: =D13+D14 | F15: =E13+E14 | G15: =F13+F14 | H15: =G13+G14
B16: Other Non-current Assets | D16: =C16*1.01 | E16: =D16*1.01 | F16: =E16*1.01 | G16: =F16*1.01 | H16: =G16*1.01
B17: Total Assets | D17: =C11+C15+C16 | E17: =D11+D15+D16 | F17: =E11+E15+E16 | G17: =F11+F15+F16 | H17: =G11+G15+G16
B19: LIABILITIES & EQUITY
B20: Trade Payables | D20: =-Forecast_IS!C8*Payable_Days/365 | E20: =-Forecast_IS!D8*Payable_Days/365 | F20: =-Forecast_IS!E8*Payable_Days/365 | G20: =-Forecast_IS!F8*Payable_Days/365 | H20: =-Forecast_IS!G8*Payable_Days/365
B21: Accrued Expenses | D21: =C20*1.02 | E21: =D20*1.02 | F21: =E20*1.02 | G21: =F20*1.02 | H21: =G20*1.02
B22: Short-term Debt | D22: =Debt_Schedule!C8 | E22: =Debt_Schedule!D8 | F22: =Debt_Schedule!E8 | G22: =Debt_Schedule!F8 | H22: =Debt_Schedule!G8
B23: Total Current Liabilities | D23: =SUM(C19:C21) | E23: =SUM(D19:D21) | F23: =SUM(E19:E21) | G23: =SUM(F19:F21) | H23: =SUM(G19:G21)
B25: Long-term Debt | D25: =Debt_Schedule!C12 | E25: =Debt_Schedule!D12 | F25: =Debt_Schedule!E12 | G25: =Debt_Schedule!F12 | H25: =Debt_Schedule!G12
B26: Other Non-current Liabilities | D26: =C24*1.01 | E26: =D24*1.01 | F26: =E24*1.01 | G26: =F24*1.01 | H26: =G24*1.01
B27: Total Liabilities | D27: =C22+C23+C24 | E27: =D22+D23+D24 | F27: =E22+E23+E24 | G27: =F22+F23+F24 | H27: =G22+G23+G24
B29: Share Capital | D29: =C27 | E29: =D27 | F29: =E27 | G29: =F27 | H29: =G27
B30: Retained Earnings | D30: =C28+Forecast_IS!C24-Forecast_CF!C22 | E30: =D28+Forecast_IS!D24-Forecast_DF!D22 | F30: =E28+Forecast_IS!E24-Forecast_EF!E22 | G30: =F28+Forecast_IS!F24-Forecast_FF!F22 | H30: =G28+Forecast_IS!G24-Forecast_GF!G22
B31: Total Equity | D31: =C27+C28 | E31: =D27+D28 | F31: =E27+E28 | G31: =F27+F28 | H31: =G27+G28
B33: Total Liabilities & Equity | D33: =C25+C29 | E33: =D25+D29 | F33: =E25+E29 | G33: =F25+F29 | H33: =G25+G29
B34: Balance Check | D34: =ROUND(C17-C30,0) | E34: =ROUND(D17-D30,0) | F34: =ROUND(E17-E30,0) | G34: =ROUND(F17-F30,0) | H34: =ROUND(G17-G30,0)

Sheet Forecast_CF
B2: Forecast Cash Flow Statement
B4: ₹ in Crores | C4: FY2025 | D4: FY2026E | E4: FY2027E | F4: FY2028E | G4: FY2029E | H4: FY2030E
B6: OPERATING ACTIVITIES
B7: Net Income | D7: =Forecast_IS!C24 | E7: =Forecast_IS!D24 | F7: =Forecast_IS!E24 | G7: =Forecast_IS!F24 | H7: =Forecast_IS!G24
B8: Depreciation & Amortization | D8: =-Forecast_IS!C15 | E8: =-Forecast_IS!D15 | F8: =-Forecast_IS!E15 | G8: =-Forecast_IS!F15 | H8: =-Forecast_IS!G15
B9: Change in Working Capital | D9: =Working_Capital!C18 | E9: =Working_Dapital!D18 | F9: =Working_Eapital!E18 | G9: =Working_Fapital!F18 | H9: =Working_Gapital!G18
B10: Other Operating Items | D10: =0 | E10: =0 | F10: =0 | G10: =0 | H10: =0
B11: Operating Cash Flow | D11: =SUM(C7:C10) | E11: =SUM(D7:D10) | F11: =SUM(E7:E10) | G11: =SUM(F7:F10) | H11: =SUM(G7:G10)
B13: INVESTING ACTIVITIES
B14: Capital Expenditure | D14: =-Forecast_IS!C6*Capex_pct_of_Revenue | E14: =-Forecast_IS!D6*Dapex_pct_of_Revenue | F14: =-Forecast_IS!E6*Eapex_pct_of_Revenue | G14: =-Forecast_IS!F6*Fapex_pct_of_Revenue | H14: =-Forecast_IS!G6*Gapex_pct_of_Revenue
B15: Acquisitions | D15: =0 | E15: =0 | F15: =0 | G15: =0 | H15: =0
B16: Other Investing | D16: =0 | E16: =0 | F16: =0 | G16: =0 | H16: =0
B17: Investing Cash Flow | D17: =SUM(C14:C16) | E17: =SUM(D14:D16) | F17: =SUM(E14:E16) | G17: =SUM(F14:F16) | H17: =SUM(G14:G16)
B19: FINANCING ACTIVITIES
B20: Debt Raised/(Repaid) | D20: =Debt_Schedule!C16 | E20: =Debt_Schedule!D16 | F20: =Debt_Schedule!E16 | G20: =Debt_Schedule!F16 | H20: =Debt_Schedule!G16
B21: Dividends Paid | D21: =-Forecast_IS!C24*0.2 | E21: =-Forecast_IS!D24*0.2 | F21: =-Forecast_IS!E24*0.2 | G21: =-Forecast_IS!F24*0.2 | H21: =-Forecast_IS!G24*0.2
B22: Equity Issuance | D22: =0 | E22: =0 | F22: =0 | G22: =0 | H22: =0
B23: Financing Cash Flow | D23: =SUM(C20:C22) | E23: =SUM(D20:D22) | F23: =SUM(E20:E22) | G23: =SUM(F20:F22) | H23: =SUM(G20:G22)
B25: NET CASH FLOW | D25: =C11+C17+C23 | E25: =D11+D17+D23 | F25: =E11+E17+E23 | G25: =F11+F17+F23 | H25: =G11+G17+G23
B26: Opening Cash | D26: =C6 | E26: =D6 | F26: =E6 | G26: =F6 | H26: =G6
B27: Closing Cash | D27: =C25+C26 | E27: =D25+D26 | F27: =E25+E26 | G27: =F25+F26 | H27: =G25+G26

Sheet Working_Capital
B2: Working Capital Schedule
C4: FY2025 | D4: FY2026E | E4: FY2027E | F4: FY2028E | G4: FY2029E | H4: FY2030E
B6: Trade Receivables | D6: =Forecast_BS!C8 | E6: =Forecast_CS!D8 | F6: =Forecast_DS!E8 | G6: =Forecast_ES!F8 | H6: =Forecast_FS!G8
B7: Inventory | D7: =Forecast_BS!C9 | E7: =Forecast_CS!D9 | F7: =Forecast_DS!E9 | G7: =Forecast_ES!F9 | H7: =Forecast_FS!G9
B8: Trade Payables | D8: =Forecast_BS!C19 | E8: =Forecast_CS!D19 | F8: =Forecast_DS!E19 | G8: =Forecast_ES!F19 | H8: =Forecast_FS!G19
B9: Net Working Capital | D9: =C6+C7+C8 | E9: =D6+D7+D8 | F9: =E6+E7+E8 | G9: =F6+F7+F8 | H9: =G6+G7+G8
B11: Change in Receivables | D11: =C6-B6 | E11: =D6-C6 | F11: =E6-D6 | G11: =F6-E6 | H11: =G6-F6
B12: Change in Inventory | D12: =C7-B7 | E12: =D7-C7 | F12: =E7-D7 | G12: =F7-E7 | H12: =G7-F7
B13: Change in Payables | D13: =C8-B8 | E13: =D8-C8 | F13: =E8-D8 | G13: =F8-E8 | H13: =G8-F8
B14: Change in Working Capital | D14: =C11+C12+C13 | E14: =D11+D12+D13 | F14: =E11+E12+E13 | G14: =F11+F12+F13 | H14: =G11+G12+G13

Sheet Debt_Schedule
B2: Debt Schedule
C4: FY2025 | D4: FY2026E | E4: FY2027E | F4: FY2028E | G4: FY2029E | H4: FY2030E
B6: SHORT-TERM DEBT
B7: Opening Balance | D7: =B8 | E7: =C8 | F7: =D8 | G7: =E8 | H7: =F8
B8: Drawdown/(Repayment) | D8: =0 | E8: =0 | F8: =0 | G8: =0 | H8: =0
B9: Closing Balance | D9: =C7+C8 | E9: =D7+D8 | F9: =E7+E8 | G9: =F7+F8 | H9: =G7+G8
B11: LONG-TERM DEBT
B12: Opening Balance | D12: =B13 | E12: =C13 | F12: =D13 | G12: =E13 | H12: =F13
B13: Drawdown/(Repayment) | D13: =0 | E13: =0 | F13: =0 | G13: =0 | H13: =0
B14: Closing Balance | D14: =C12+C13 | E14: =D12+D13 | F14: =E12+E13 | G14: =F12+F13 | H14: =G12+G13
B16: TOTAL DEBT | D16: =C9+C14 | E16: =D9+D14 | F16: =E9+E14 | G16: =F9+F14 | H16: =G9+G14
B17: Net Change in Debt | D17: =C8+C13 | E17: =D8+D13 | F17: =E8+E13 | G17: =F8+F13 | H17: =G8+G13
B19: INTEREST EXPENSE
B20: Interest on Short-term | D20: =(C7+C9)/2*Cost_of_Debt | E20: =(D7+D9)/2*Dost_of_Debt | F20: =(E7+E9)/2*Eost_of_Debt | G20: =(F7+F9)/2*Fost_of_Debt | H20: =(G7+G9)/2*Gost_of_Debt
B21: Interest on Long-term | D21: =(C12+C14)/2*Cost_of_Debt | E21: =(D12+D14)/2*Dost_of_Debt | F21: =(E12+E14)/2*Eost_of_Debt | G21: =(F12+F14)/2*Fost_of_Debt | H21: =(G12+G14)/2*Gost_of_Debt
B22: Total Interest | D22: =C20+C21 | E22: =D20+D21 | F22: =E20+E21 | G22: =F20+F21 | H22: =G20+G21

Sheet Valuation
B2: Valuation Analysis
B5: WACC Calculation
B6: Risk-free Rate | C6: =Risk_free_Rate
B7: Equity Risk Premium | C7: =Equity_Risk_Premium
B8: Beta | C8: =Beta
B9: Cost of Equity | C9: =C6+C7*C8
B11: Cost of Debt (pre-tax) | C11: =Cost_of_Debt
B12: Tax Rate | C12: =Tax_Rate
B13: Cost of Debt (post-tax) | C13: =C11*(1-C12)
B15: Target Debt/Equity | C15: =0.5
B16: Weight of Equity | C16: =1/(1+C14)
B17: Weight of Debt | C17: =C14/(1+C14)
B19: WACC | C19: =C15*C9+C16*C13
B22: DCF Valuation
C23: Year 1 | D23: Year 2 | E23: Year 3 | F23: Year 4 | G23: Year 5 | H23: Terminal
B24: Free Cash Flow to Firm | C24: =Forecast_IS!C12-Forecast_CF!C14+Forecast_CF!C9 | D24: =Forecast_IS!D12-Forecast_CF!D14+Forecast_CF!D9 | E24: =Forecast_IS!E12-Forecast_CF!E14+Forecast_CF!E9 | F24: =Forecast_IS!F12-Forecast_CF!F14+Forecast_CF!F9 | G24: =Forecast_IS!G12-Forecast_CF!G14+Forecast_CF!G9
B25: Discount Factor | C25: =1/(1+$C$18)^1 | D25: =1/(1+$C$18)^2 | E25: =1/(1+$C$18)^3 | F25: =1/(1+$C$18)^4 | G25: =1/(1+$C$18)^5
B26: Present Value of FCFF | C26: =C24*C25 | D26: =D24*D25 | E26: =E24*E25 | F26: =F24*F25 | G26: =G24*G25
B28: Terminal Growth Rate | C28: =Terminal_Growth
B29: Terminal Value | C29: =IFERROR(G24*(1+C28)/($C$18-C28),0)
B30: PV of Terminal Value | C30: =C29*G25
B32: Valuation Summary
B33: Sum of PV of FCFF | C33: =SUM(C26:G26)
B34: PV of Terminal Value | C34: =C31
B35: Enterprise Value | C35: =C33+C34
B36: Less: Net Debt | C36: =Debt_Schedule!C15-Forecast_BS!C7
B37: Equity Value | C37: =C35-C36
B38: Shares Outstanding (Cr) | C38: =10
B39: Implied Share Price | C39: =IFERROR(C37/C38*10000000,0)

Sheet Dashboard
B2: ADANIPOWER - Financial Dashboard
B4: Key charts and metrics will be displayed here.
B6: Note: Charts are best viewed after populating the model with actual data.
