Workbook
Name Revenue_Growth_Rate: 'Assumptions'!$C$7
Name Volume_Growth: 'Assumptions'!$C$8
Name Price_Inflation: 'Assumptions'!$C$9
Name Gross_Margin: 'Assumptions'!$C$12
Name EBITDA_Margin: 'Assumptions'!$C$13
Name SGAndA_as_Pct_of_Revenue: 'Assumptions'!$C$14
Name Receivable_Days: 'Assumptions'!$C$17
Name Inventory_Days: 'Assumptions'!$C$18
Name Payable_Days: 'Assumptions'!$C$19
Name Capex_Pct_of_Revenue: 'Assumptions'!$C$22
Name DAndA_Pct_of_Gross_PPE: 'Assumptions'!$C$23
Name Cost_of_Debt: 'Assumptions'!$C$26
Name Debt_Equity_Target: 'Assumptions'!$C$27
Name Risk-free_Rate: 'Assumptions'!$C$30
Name Equity_Risk_Premium: 'Assumptions'!$C$31
Name Beta: 'Assumptions'!$C$32
Name Terminal_Growth_Rate: 'Assumptions'!$C$33
Name Tax_Rate: 'Assumptions'!$C$34
Name Shares_Outstanding_(Cr): 'Assumptions'!$C$37

Sheet Summary
B2: HDFCBANK
B3: Financial Model Summary
B4: Generated: 29-Jan-2026
B7: Company Information | E7: Model Navigation
B8: Industry | C8: Banking & Financial Services | E8: Summary
B9: Model Type | C9: Banking | E9: Assumptions
B10: Forecast Period | C10: 5 Years | E10: Income Statement
E11: Balance Sheet
B12: Key Outputs | E12: Cash Flow
B13: Implied Share Price | C13: =Valuation!C50 | E13: Valuation
B14: Enterprise Value | C14: =Valuation!C44 | E14: Sensitivity
B15: Equity Value | C15: =Valuation!C46 | E15: Scenarios
B16: WACC | C16: =Valuation!C19 | E16: Dashboard

Sheet Assumptions
B2: Model Assumptions
B4: Yellow cells are inputs - modify to update the model
B6: GROWTH ASSUMPTIONS
B7: Revenue Growth Rate | C7: 0.1 | D7: percent | E7: Annual revenue growth
B8: Volume Growth | C8: 0.05 | D8: percent | E8: Unit volume growth
B9: Price Inflation | C9: 0.03 | D9: percent | E9: Price increase per year
B11: MARGIN ASSUMPTIONS
B12: Gross Margin | C12: 0.35 | D12: percent | E12: Revenue - COGS
B13: EBITDA Margin | C13: 0.25 | D13: percent | E13: Target EBITDA margin
B14: SG&A as % of Revenue | C14: 0.08 | D14: percent | E14: Operating expenses
B16: WORKING CAPITAL
B17: Receivable Days | C17: 45 | D17: days | E17: DSO
B18: Inventory Days | C18: 30 | D18: days | E18: DIO
B19: Payable Days | C19: 60 | D19: days | E19: DPO
B21: CAPEX & D&A
B22: Capex % of Revenue | C22: 0.05 | D22: percent | E22: Maintenance + growth capex
B23: D&A % of Gross PPE | C23: 0.08 | D23: percent | E23: Depreciation rate
B25: DEBT ASSUMPTIONS
B26: Cost of Debt | C26: 0.09 | D26: percent | E26: Interest rate on debt
B27: Debt/Equity Target | C27: 0.5 | D27: ratio | E27: Leverage ratio
B29: VALUATION INPUTS
B30: Risk-free Rate | C30: 0.07 | D30: percent | E30: 10Y G-Sec rate
B31: Equity Risk Premium | C31: 0.055 | D31: percent | E31: Market risk premium
B32: Beta | C32: 1 | D32: ratio | E32: Levered beta
B33: Terminal Growth Rate | C33: 0.04 | D33: percent | E33: Long-term growth
B34: Tax Rate | C34: 0.25 | D34: percent | E34: Effective tax rate
B36: SHARES
B37: Shares Outstanding (Cr) | C37: 10 | D37: number | E37: Diluted shares

Sheet Income_Statement
B2: Income Statement (₹ Crores)
C4: FY2021 | D4: FY2022 | E4: FY2023 | F4: FY2024 | G4: FY2025 | H4: FY2026E | I4: FY2027E | J4: FY2028E | K4: FY2029E | L4: FY2030E
B6: Revenue | C6: 10000 | D6: =IFERROR(C6*(1+Assumptions!$C$7),0) | E6: =IFERROR(D6*(1+Assumptions!$C$7),0) | F6: =IFERROR(E6*(1+Assumptions!$C$7),0) | G6: =IFERROR(F6*(1+Assumptions!$C$7),0) | H6: =IFERROR(G6*(1+Assumptions!$C$7),0) | I6: =IFERROR(H6*(1+Assumptions!$C$7),0) | J6: =IFERROR(I6*(1+Assumptions!$C$7),0) | K6: =IFERROR(J6*(1+Assumptions!$C$7),0) | L6: =IFERROR(K6*(1+Assumptions!$C$7),0)
B7: Growth % | D7: =IFERROR(D6/C6-1,0) | E7: =IFERROR(E6/D6-1,0) | F7: =IFERROR(F6/E6-1,0) | G7: =IFERROR(G6/F6-1,0) | H7: =IFERROR(H6/G6-1,0) | I7: =IFERROR(I6/H6-1,0) | J7: =IFERROR(J6/I6-1,0) | K7: =IFERROR(K6/J6-1,0) | L7: =IFERROR(L6/K6-1,0)
B9: Cost of Goods Sold | C9: =IFERROR(-C6*(1-Assumptions!$C$12),0) | D9: =IFERROR(-D6*(1-Assumptions!$C$12),0) | E9: =IFERROR(-E6*(1-Assumptions!$C$12),0) | F9: =IFERROR(-F6*(1-Assumptions!$C$12),0) | G9: =IFERROR(-G6*(1-Assumptions!$C$12),0) | H9: =IFERROR(-H6*(1-Assumptions!$C$12),0) | I9: =IFERROR(-I6*(1-Assumptions!$C$12),0) | J9: =IFERROR(-J6*(1-Assumptions!$C$12),0) | ... L9: =IFERROR(-L6*(1-Assumptions!$C$12),0)
B10: Gross Profit | C10: =C6+C9 | D10: =D6+D9 | E10: =E6+E9 | F10: =F6+F9 | G10: =G6+G9 | H10: =H6+H9 | I10: =I6+I9 | J10: =J6+J9 | ... L10: =L6+L9
B11: Gross Margin % | C11: =IFERROR(C10/C6,0) | D11: =IFERROR(D10/D6,0) | E11: =IFERROR(E10/E6,0) | F11: =IFERROR(F10/F6,0) | G11: =IFERROR(G10/G6,0) | H11: =IFERROR(H10/H6,0) | I11: =IFERROR(I10/I6,0) | J11: =IFERROR(J10/J6,0) | ... L11: =IFERROR(L10/L6,0)
B13: SG&A Expenses | C13: =IFERROR(-C6*Assumptions!$C$14,0) | D13: =IFERROR(-D6*Assumptions!$C$14,0) | E13: =IFERROR(-E6*Assumptions!$C$14,0) | F13: =IFERROR(-F6*Assumptions!$C$14,0) | G13: =IFERROR(-G6*Assumptions!$C$14,0) | H13: =IFERROR(-H6*Assumptions!$C$14,0) | I13: =IFERROR(-I6*Assumptions!$C$14,0) | J13: =IFERROR(-J6*Assumptions!$C$14,0) | ... L13: =IFERROR(-L6*Assumptions!$C$14,0)
B14: Other Operating Expenses | C14: =-C6*0.02 | D14: =-D6*0.02 | E14: =-E6*0.02 | F14: =-F6*0.02 | G14: =-G6*0.02 | H14: =-H6*0.02 | I14: =-I6*0.02 | J14: =-J6*0.02 | ... L14: =-L6*0.02
B15: EBITDA | C15: =C10+C13+C14 | D15: =D10+D13+D14 | E15: =E10+E13+E14 | F15: =F10+F13+F14 | G15: =G10+G13+G14 | H15: =H10+H13+H14 | I15: =I10+I13+I14 | J15: =J10+J13+J14 | ... L15: =L10+L13+L14
B16: EBITDA Margin % | C16: =IFERROR(C15/C6,0) | D16: =IFERROR(D15/D6,0) | E16: =IFERROR(E15/E6,0) | F16: =IFERROR(F15/F6,0) | G16: =IFERROR(G15/G6,0) | H16: =IFERROR(H15/H6,0) | I16: =IFERROR(I15/I6,0) | J16: =IFERROR(J15/J6,0) | ... L16: =IFERROR(L15/L6,0)
B18: Depreciation & Amortization | C18: =IFERROR(-C6*Assumptions!$C$23,0) | D18: =IFERROR(-D6*Assumptions!$C$23,0) | E18: =IFERROR(-E6*Assumptions!$C$23,0) | F18: =IFERROR(-F6*Assumptions!$C$23,0) | G18: =IFERROR(-G6*Assumptions!$C$23,0) | H18: =IFERROR(-H6*Assumptions!$C$23,0) | I18: =IFERROR(-I6*Assumptions!$C$23,0) | J18: =IFERROR(-J6*Assumptions!$C$23,0) | ... L18: =IFERROR(-L6*Assumptions!$C$23,0)
B19: EBIT | C19: =C15+C18 | D19: =D15+D18 | E19: =E15+E18 | F19: =F15+F18 | G19: =G15+G18 | H19: =H15+H18 | I19: =I15+I18 | J19: =J15+J18 | ... L19: =L15+L18
B20: EBIT Margin % | C20: =IFERROR(C19/C6,0) | D20: =IFERROR(D19/D6,0) | E20: =IFERROR(E19/E6,0) | F20: =IFERROR(F19/F6,0) | G20: =IFERROR(G19/G6,0) | H20: =IFERROR(H19/H6,0) | I20: =IFERROR(I19/I6,0) | J20: =IFERROR(J19/J6,0) | ... L20: =IFERROR(L19/L6,0)
B22: Interest Expense | C22: =-C6*0.02 | D22: =-D6*0.02 | E22: =-E6*0.02 | F22: =-F6*0.02 | G22: =-G6*0.02 | H22: =-H6*0.02 | I22: =-I6*0.02 | J22: =-J6*0.02 | ... L22: =-L6*0.02
B23: Pre-tax Income | C23: =C19+C22 | D23: =D19+D22 | E23: =E19+E22 | F23: =F19+F22 | G23: =G19+G22 | H23: =H19+H22 | I23: =I19+I22 | J23: =J19+J22 | ... L23: =L19+L22
B25: Tax Expense | C25: =IFERROR(-MAX(C23,0)*Assumptions!$C$34,0) | D25: =IFERROR(-MAX(D23,0)*Assumptions!$C$34,0) | E25: =IFERROR(-MAX(E23,0)*Assumptions!$C$34,0) | F25: =IFERROR(-MAX(F23,0)*Assumptions!$C$34,0) | G25: =IFERROR(-MAX(G23,0)*Assumptions!$C$34,0) | H25: =IFERROR(-MAX(H23,0)*Assumptions!$C$34,0) | I25: =IFERROR(-MAX(I23,0)*Assumptions!$C$34,0) | J25: =IFERROR(-MAX(J23,0)*Assumptions!$C$34,0) | ... L25: =IFERROR(-MAX(L23,0)*Assumptions!$C$34,0)
B26: Net Income | C26: =C23+C25 | D26: =D23+D25 | E26: =E23+E25 | F26: =F23+F25 | G26: =G23+G25 | H26: =H23+H25 | I26: =I23+I25 | J26: =J23+J25 | ... L26: =L23+L25
B27: Net Margin % | C27: =IFERROR(C26/C6,0) | D27: =IFERROR(D26/D6,0) | E27: =IFERROR(E26/E6,0) | F27: =IFERROR(F26/F6,0) | G27: =IFERROR(G26/G6,0) | H27: =IFERROR(H26/H6,0) | I27: =IFERROR(I26/I6,0) | J27: =IFERROR(J26/J6,0) | ... L27: =IFERROR(L26/L6,0)

Sheet Balance_Sheet
B2: Balance Sheet (₹ Crores)
C4: FY2021 | D4: FY2022 | E4: FY2023 | F4: FY2024 | G4: FY2025 | H4: FY2026E | I4: FY2027E | J4: FY2028E | K4: FY2029E | L4: FY2030E
B6: ASSETS
B7: Cash & Equivalents | C7: 2000 | D7: =C7+Cash_Flow!D28 | E7: =D7+Cash_Flow!E28 | F7: =E7+Cash_Flow!F28 | G7: =F7+Cash_Flow!G28 | H7: =G7+Cash_Flow!H28 | I7: =H7+Cash_Flow!I28 | J7: =I7+Cash_Flow!J28 | K7: =J7+Cash_Flow!K28 | L7: =K7+Cash_Flow!L28
B8: Trade Receivables | C8: =IFERROR(Income_Statement!C6*Assumptions!$C$17/365,0) | D8: =IFERROR(Income_Statement!D6*Assumptions!$C$17/365,0) | E8: =IFERROR(Income_Statement!E6*Assumptions!$C$17/365,0) | F8: =IFERROR(Income_Statement!F6*Assumptions!$C$17/365,0) | G8: =IFERROR(Income_Statement!G6*Assumptions!$C$17/365,0) | H8: =IFERROR(Income_Statement!H6*Assumptions!$C$17/365,0) | I8: =IFERROR(Income_Statement!I6*Assumptions!$C$17/365,0) | J8: =IFERROR(Income_Statement!J6*Assumptions!$C$17/365,0) | ... L8: =IFERROR(Income_Statement!L6*Assumptions!$C$17/365,0)
B9: Inventory | C9: =IFERROR(ABS(Income_Statement!C9)*Assumptions!$C$18/365,0) | D9: =IFERROR(ABS(Income_Statement!D9)*Assumptions!$C$18/365,0) | E9: =IFERROR(ABS(Income_Statement!E9)*Assumptions!$C$18/365,0) | F9: =IFERROR(ABS(Income_Statement!F9)*Assumptions!$C$18/365,0) | G9: =IFERROR(ABS(Income_Statement!G9)*Assumptions!$C$18/365,0) | H9: =IFERROR(ABS(Income_Statement!H9)*Assumptions!$C$18/365,0) | I9: =IFERROR(ABS(Income_Statement!I9)*Assumptions!$C$18/365,0) | J9: =IFERROR(ABS(Income_Statement!J9)*Assumptions!$C$18/365,0) | ... L9: =IFERROR(ABS(Income_Statement!L9)*Assumptions!$C$18/365,0)
B10: Other Current Assets | C10: 1000 | D10: =C10*1.02 | E10: =D10*1.02 | F10: =E10*1.02 | G10: =F10*1.02 | H10: =G10*1.02 | I10: =H10*1.02 | J10: =I10*1.02 | K10: =J10*1.02 | L10: =K10*1.02
B11: Total Current Assets | C11: =SUM(C7:C10) | D11: =SUM(D7:D10) | E11: =SUM(E7:E10) | F11: =SUM(F7:F10) | G11: =SUM(G7:G10) | H11: =SUM(H7:H10) | I11: =SUM(I7:I10) | J11: =SUM(J7:J10) | ... L11: =SUM(L7:L10)
B13: Gross PP&E | C13: 12000 | D13: =IFERROR(C13+Income_Statement!D6*Assumptions!$C$22,C13) | E13: =IFERROR(D13+Income_Statement!E6*Assumptions!$C$22,D13) | F13: =IFERROR(E13+Income_Statement!F6*Assumptions!$C$22,E13) | G13: =IFERROR(F13+Income_Statement!G6*Assumptions!$C$22,F13) | H13: =IFERROR(G13+Income_Statement!H6*Assumptions!$C$22,G13) | I13: =IFERROR(H13+Income_Statement!I6*Assumptions!$C$22,H13) | J13: =IFERROR(I13+Income_Statement!J6*Assumptions!$C$22,I13) | K13: =IFERROR(J13+Income_Statement!K6*Assumptions!$C$22,J13) | L13: =IFERROR(K13+Income_Statement!L6*Assumptions!$C$22,K13)
B14: Accumulated Depreciation | C14: -4000 | D14: =C14+Income_Statement!D18 | E14: =D14+Income_Statement!E18 | F14: =E14+Income_Statement!F18 | G14: =F14+Income_Statement!G18 | H14: =G14+Income_Statement!H18 | I14: =H14+Income_Statement!I18 | J14: =I14+Income_Statement!J18 | K14: =J14+Income_Statement!K18 | L14: =K14+Income_Statement!L18
B15: Net PP&E | C15: =C13+C14 | D15: =D13+D14 | E15: =E13+E14 | F15: =F13+F14 | G15: =G13+G14 | H15: =H13+H14 | I15: =I13+I14 | J15: =J13+J14 | ... L15: =L13+L14
B16: Other Non-Current Assets | C16: 2000 | D16: =C16*1.01 | E16: =D16*1.01 | F16: =E16*1.01 | G16: =F16*1.01 | H16: =G16*1.01 | I16: =H16*1.01 | J16: =I16*1.01 | K16: =J16*1.01 | L16: =K16*1.01
B17: Total Assets | C17: =C11+C15+C16 | D17: =D11+D15+D16 | E17: =E11+E15+E16 | F17: =F11+F15+F16 | G17: =G11+G15+G16 | H17: =H11+H15+H16 | I17: =I11+I15+I16 | J17: =J11+J15+J16 | ... L17: =L11+L15+L16
B19: LIABILITIES
B20: Trade Payables | C20: =IFERROR(ABS(Income_Statement!C9)*Assumptions!$C$19/365,0) | D20: =IFERROR(ABS(Income_Statement!D9)*Assumptions!$C$19/365,0) | E20: =IFERROR(ABS(Income_Statement!E9)*Assumptions!$C$19/365,0) | F20: =IFERROR(ABS(Income_Statement!F9)*Assumptions!$C$19/365,0) | G20: =IFERROR(ABS(Income_Statement!G9)*Assumptions!$C$19/365,0) | H20: =IFERROR(ABS(Income_Statement!H9)*Assumptions!$C$19/365,0) | I20: =IFERROR(ABS(Income_Statement!I9)*Assumptions!$C$19/365,0) | J20: =IFERROR(ABS(Income_Statement!J9)*Assumptions!$C$19/365,0) | ... L20: =IFERROR(ABS(Income_Statement!L9)*Assumptions!$C$19/365,0)
B21: Accrued Expenses | C21: 600 | D21: =C21*1.02 | E21: =D21*1.02 | F21: =E21*1.02 | G21: =F21*1.02 | H21: =G21*1.02 | I21: =H21*1.02 | J21: =I21*1.02 | K21: =J21*1.02 | L21: =K21*1.02
B22: Short-term Debt | C22: 1000 | D22: =C22 | E22: =D22 | F22: =E22 | G22: =F22 | H22: =G22 | I22: =H22 | J22: =I22 | K22: =J22 | L22: =K22
B23: Total Current Liabilities | C23: =C20+C21+C22 | D23: =D20+D21+D22 | E23: =E20+E21+E22 | F23: =F20+F21+F22 | G23: =G20+G21+G22 | H23: =H20+H21+H22 | I23: =I20+I21+I22 | J23: =J20+J21+J22 | ... L23: =L20+L21+L22
B25: Long-term Debt | C25: 5000 | D25: =C25 | E25: =D25 | F25: =E25 | G25: =F25 | H25: =G25 | I25: =H25 | J25: =I25 | K25: =J25 | L25: =K25
B26: Other Non-Current Liabilities | C26: 400 | D26: =C26*1.01 | E26: =D26*1.01 | F26: =E26*1.01 | G26: =F26*1.01 | H26: =G26*1.01 | I26: =H26*1.01 | J26: =I26*1.01 | K26: =J26*1.01 | L26: =K26*1.01
B27: Total Liabilities | C27: =C23+C25+C26 | D27: =D23+D25+D26 | E27: =E23+E25+E26 | F27: =F23+F25+F26 | G27: =G23+G25+G26 | H27: =H23+H25+H26 | I27: =I23+I25+I26 | J27: =J23+J25+J26 | ... L27: =L23+L25+L26
B29: EQUITY
B30: Share Capital | C30: 4000 | D30: =C30 | E30: =D30 | F30: =E30 | G30: =F30 | H30: =G30 | I30: =H30 | J30: =I30 | K30: =J30 | L30: =K30
B31: Retained Earnings | C31: 9000 | D31: =C31+Income_Statement!D26-Income_Statement!D26*0.2 | E31: =D31+Income_Statement!E26-Income_Statement!E26*0.2 | F31: =E31+Income_Statement!F26-Income_Statement!F26*0.2 | G31: =F31+Income_Statement!G26-Income_Statement!G26*0.2 | H31: =G31+Income_Statement!H26-Income_Statement!H26*0.2 | I31: =H31+Income_Statement!I26-Income_Statement!I26*0.2 | J31: =I31+Income_Statement!J26-Income_Statement!J26*0.2 | K31: =J31+Income_Statement!K26-Income_Statement!K26*0.2 | L31: =K31+Income_Statement!L26-Income_Statement!L26*0.2
B32: Total Equity | C32: =C30+C31 | D32: =D30+D31 | E32: =E30+E31 | F32: =F30+F31 | G32: =G30+G31 | H32: =H30+H31 | I32: =I30+I31 | J32: =J30+J31 | ... L32: =L30+L31
B34: Total Liabilities & Equity | C34: =C27+C32 | D34: =D27+D32 | E34: =E27+E32 | F34: =F27+F32 | G34: =G27+G32 | H34: =H27+H32 | I34: =I27+I32 | J34: =J27+J32 | ... L34: =L27+L32
B35: Balance Check (should be 0) | C35: =ROUND(C17-C34,0) | D35: =ROUND(D17-D34,0) | E35: =ROUND(E17-E34,0) | F35: =ROUND(F17-F34,0) | G35: =ROUND(G17-G34,0) | H35: =ROUND(H17-H34,0) | I35: =ROUND(I17-I34,0) | J35: =ROUND(J17-J34,0) | ... L35: =ROUND(L17-L34,0)

Sheet Cash_Flow
B2: Cash Flow Statement (₹ Crores)
C4: FY2021 | D4: FY2022 | E4: FY2023 | F4: FY2024 | G4: FY2025 | H4: FY2026E | I4: FY2027E | J4: FY2028E | K4: FY2029E | L4: FY2030E
B6: OPERATING ACTIVITIES
B7: Net Income | C7: =Income_Statement!C26 | D7: =Income_Statement!D26 | E7: =Income_Statement!E26 | F7: =Income_Statement!F26 | G7: =Income_Statement!G26 | H7: =Income_Statement!H26 | I7: =Income_Statement!I26 | J7: =Income_Statement!J26 | ... L7: =Income_Statement!L26
B8: Add: Depreciation | C8: =-Income_Statement!C18 | D8: =-Income_Statement!D18 | E8: =-Income_Statement!E18 | F8: =-Income_Statement!F18 | G8: =-Income_Statement!G18 | H8: =-Income_Statement!H18 | I8: =-Income_Statement!I18 | J8: =-Income_Statement!J18 | ... L8: =-Income_Statement!L18
B9: Change in Receivables | C9: 0 | D9: =-(D7/Income_Statement!D6)*Balance_Sheet!D8+(C7/Income_Statement!C6)*Balance_Sheet!C8 | E9: =-(E7/Income_Statement!E6)*Balance_Sheet!E8+(D7/Income_Statement!D6)*Balance_Sheet!D8 | F9: =-(F7/Income_Statement!F6)*Balance_Sheet!F8+(E7/Income_Statement!E6)*Balance_Sheet!E8 | G9: =-(G7/Income_Statement!G6)*Balance_Sheet!G8+(F7/Income_Statement!F6)*Balance_Sheet!F8 | H9: =-(H7/Income_Statement!H6)*Balance_Sheet!H8+(G7/Income_Statement!G6)*Balance_Sheet!G8 | I9: =-(I7/Income_Statement!I6)*Balance_Sheet!I8+(H7/Income_Statement!H6)*Balance_Sheet!H8 | J9: =-(J7/Income_Statement!J6)*Balance_Sheet!J8+(I7/Income_Statement!I6)*Balance_Sheet!I8 | K9: =-(K7/Income_Statement!K6)*Balance_Sheet!K8+(J7/Income_Statement!J6)*Balance_Sheet!J8 | L9: =-(L7/Income_Statement!L6)*Balance_Sheet!L8+(K7/Income_Statement!K6)*Balance_Sheet!K8
B10: Change in Inventory | C10: 0 | D10: =Balance_Sheet!C9-Balance_Sheet!D9 | E10: =Balance_Sheet!D9-Balance_Sheet!E9 | F10: =Balance_Sheet!E9-Balance_Sheet!F9 | G10: =Balance_Sheet!F9-Balance_Sheet!G9 | H10: =Balance_Sheet!G9-Balance_Sheet!H9 | I10: =Balance_Sheet!H9-Balance_Sheet!I9 | J10: =Balance_Sheet!I9-Balance_Sheet!J9 | K10: =Balance_Sheet!J9-Balance_Sheet!K9 | L10: =Balance_Sheet!K9-Balance_Sheet!L9
B11: Change in Payables | C11: 0 | D11: =Balance_Sheet!D20-Balance_Sheet!C20 | E11: =Balance_Sheet!E20-Balance_Sheet!D20 | F11: =Balance_Sheet!F20-Balance_Sheet!E20 | G11: =Balance_Sheet!G20-Balance_Sheet!F20 | H11: =Balance_Sheet!H20-Balance_Sheet!G20 | I11: =Balance_Sheet!I20-Balance_Sheet!H20 | J11: =Balance_Sheet!J20-Balance_Sheet!I20 | K11: =Balance_Sheet!K20-Balance_Sheet!J20 | L11: =Balance_Sheet!L20-Balance_Sheet!K20
B12: Change in Other Working Capital | C12: 0 | D12: 0 | E12: 0 | F12: 0 | G12: 0 | H12: 0 | I12: 0 | J12: 0 | K12: 0 | L12: 0
B13: Operating Cash Flow | C13: =SUM(C7:C12) | D13: =SUM(D7:D12) | E13: =SUM(E7:E12) | F13: =SUM(F7:F12) | G13: =SUM(G7:G12) | H13: =SUM(H7:H12) | I13: =SUM(I7:I12) | J13: =SUM(J7:J12) | ... L13: =SUM(L7:L12)
B15: INVESTING ACTIVITIES
B16: Capital Expenditure | C16: =-Income_Statement!C6*Assumptions!$C$21 | D16: =-Income_Statement!D6*Assumptions!$C$21 | E16: =-Income_Statement!E6*Assumptions!$C$21 | F16: =-Income_Statement!F6*Assumptions!$C$21 | G16: =-Income_Statement!G6*Assumptions!$C$21 | H16: =-Income_Statement!H6*Assumptions!$C$21 | I16: =-Income_Statement!I6*Assumptions!$C$21 | J16: =-Income_Statement!J6*Assumptions!$C$21 | ... L16: =-Income_Statement!L6*Assumptions!$C$21
B17: Other Investing | C17: 0 | D17: 0 | E17: 0 | F17: 0 | G17: 0 | H17: 0 | I17: 0 | J17: 0 | K17: 0 | L17: 0
B18: Investing Cash Flow | C18: =C16+C17 | D18: =D16+D17 | E18: =E16+E17 | F18: =F16+F17 | G18: =G16+G17 | H18: =H16+H17 | I18: =I16+I17 | J18: =J16+J17 | ... L18: =L16+L17
B20: FINANCING ACTIVITIES
B21: Dividends Paid | C21: =-Income_Statement!C26*0.2 | D21: =-Income_Statement!D26*0.2 | E21: =-Income_Statement!E26*0.2 | F21: =-Income_Statement!F26*0.2 | G21: =-Income_Statement!G26*0.2 | H21: =-Income_Statement!H26*0.2 | I21: =-Income_Statement!I26*0.2 | J21: =-Income_Statement!J26*0.2 | ... L21: =-Income_Statement!L26*0.2
B22: Change in Debt | C22: 0 | D22: 0 | E22: 0 | F22: 0 | G22: 0 | H22: 0 | I22: 0 | J22: 0 | K22: 0 | L22: 0
B23: Financing Cash Flow | C23: =C21+C22 | D23: =D21+D22 | E23: =E21+E22 | F23: =F21+F22 | G23: =G21+G22 | H23: =H21+H22 | I23: =I21+I22 | J23: =J21+J22 | ... L23: =L21+L22
B25: Net Change in Cash | C25: =C13+C18+C23 | D25: =D13+D18+D23 | E25: =E13+E18+E23 | F25: =F13+F18+F23 | G25: =G13+G18+G23 | H25: =H13+H18+H23 | I25: =I13+I18+I23 | J25: =J13+J18+J23 | ... L25: =L13+L18+L23
B26: Opening Cash | C26: 2000 | D26: =Balance_Sheet!C7 | E26: =Balance_Sheet!D7 | F26: =Balance_Sheet!E7 | G26: =Balance_Sheet!F7 | H26: =Balance_Sheet!G7 | I26: =Balance_Sheet!H7 | J26: =Balance_Sheet!I7 | K26: =Balance_Sheet!J7 | L26: =Balance_Sheet!K7
B27: Closing Cash | C27: =C26+C25 | D27: =D26+D25 | E27: =E26+E25 | F27: =F26+F25 | G27: =G26+G25 | H27: =H26+H25 | I27: =I26+I25 | J27: =J26+J25 | ... L27: =L26+L25

Sheet Valuation
B2: DCF Valuation (₹ Crores)
B5: WACC CALCULATION
B6: Risk-free Rate | C6: =Assumptions!$C$30
B7: Equity Risk Premium | C7: =Assumptions!$C$31
B8: Beta | C8: =Assumptions!$C$32
B9: Cost of Equity | C9: =C6+C7*C8
B11: Cost of Debt (pre-tax) | C11: =Assumptions!$C$26
B12: Tax Rate | C12: =Assumptions!$C$34
B13: Cost of Debt (post-tax) | C13: =C11*(1-C12)
B15: Target D/E Ratio | C15: =Assumptions!$C$27
B16: Weight of Equity | C16: =1/(1+C15)
B17: Weight of Debt | C17: =C15/(1+C15)
B19: WACC | C19: =C16*C9+C17*C13
B22: DCF VALUATION
C23: Year 1 | D23: Year 2 | E23: Year 3 | F23: Year 4 | G23: Year 5
B24: Free Cash Flow to Firm | C24: =Income_Statement!H15+Income_Statement!H18+Cash_Flow!H19 | D24: =Income_Statement!I15+Income_Statement!I18+Cash_Flow!I19 | E24: =Income_Statement!J15+Income_Statement!J18+Cash_Flow!J19 | F24: =Income_Statement!K15+Income_Statement!K18+Cash_Flow!K19 | G24: =Income_Statement!L15+Income_Statement!L18+Cash_Flow!L19
B25: Discount Factor | C25: =1/(1+$C$19)^1 | D25: =1/(1+$C$19)^2 | E25: =1/(1+$C$19)^3 | F25: =1/(1+$C$19)^4 | G25: =1/(1+$C$19)^5
B26: Present Value of FCFF | C26: =C24*C25 | D26: =D24*D25 | E26: =E24*E25 | F26: =F24*F25 | G26: =G24*G25
B28: Terminal Growth Rate | C28: =Assumptions!$C$33
B29: Terminal Value | C29: =IFERROR(G24*(1+C28)/($C$19-C28),0)
B30: PV of Terminal Value | C30: =C29*G25
B32: VALUATION SUMMARY
B33: Sum of PV of FCFF | C33: =SUM(C26:G26)
B34: PV of Terminal Value | C34: =C31
B35: Enterprise Value | C35: =C33+C34
B36: Less: Net Debt | C36: =Balance_Sheet!L25+Balance_Sheet!L22-Balance_Sheet!L7
B37: Equity Value | C37: =C35+C36
B39: Shares Outstanding (Cr) | C39: =Assumptions!$C$37
B40: Implied Share Price (₹) | C40: =IFERROR(C37/C39*10,0)

Sheet Sensitivity
B2: Sensitivity Analysis
B5: WACC vs Terminal Growth Sensitivity
B7: WACC \ TG | C7: 0.02 | D7: 0.025 | E7: 0.03 | F7: 0.035 | G7: 0.04 | H7: 0.045 | I7: 0.05
B8: 0.08 | C8: =IFERROR(1000*(1+0.02)/(0.08-0.02),0) | D8: =IFERROR(1000*(1+0.025)/(0.08-0.025),0) | E8: =IFERROR(1000*(1+0.03)/(0.08-0.03),0) | F8: =IFERROR(1000*(1+0.035)/(0.08-0.035),0) | G8: =IFERROR(1000*(1+0.04)/(0.08-0.04),0) | H8: =IFERROR(1000*(1+0.045)/(0.08-0.045),0) | I8: =IFERROR(1000*(1+0.05)/(0.08-0.05),0)
B9: 0.09 | C9: =IFERROR(1000*(1+0.02)/(0.09-0.02),0) | D9: =IFERROR(1000*(1+0.025)/(0.09-0.025),0) | E9: =IFERROR(1000*(1+0.03)/(0.09-0.03),0) | F9: =IFERROR(1000*(1+0.035)/(0.09-0.035),0) | G9: =IFERROR(1000*(1+0.04)/(0.09-0.04),0) | H9: =IFERROR(1000*(1+0.045)/(0.09-0.045),0) | I9: =IFERROR(1000*(1+0.05)/(0.09-0.05),0)
B10: 0.1 | C10: =IFERROR(1000*(1+0.02)/(0.1-0.02),0) | D10: =IFERROR(1000*(1+0.025)/(0.1-0.025),0) | E10: =IFERROR(1000*(1+0.03)/(0.1-0.03),0) | F10: =IFERROR(1000*(1+0.035)/(0.1-0.035),0) | G10: =IFERROR(1000*(1+0.04)/(0.1-0.04),0) | H10: =IFERROR(1000*(1+0.045)/(0.1-0.045),0) | I10: =IFERROR(1000*(1+0.05)/(0.1-0.05),0)
B11: 0.11 | C11: =IFERROR(1000*(1+0.02)/(0.11-0.02),0) | D11: =IFERROR(1000*(1+0.025)/(0.11-0.025),0) | E11: =IFERROR(1000*(1+0.03)/(0.11-0.03),0) | F11: =IFERROR(1000*(1+0.035)/(0.11-0.035),0) | G11: =IFERROR(1000*(1+0.04)/(0.11-0.04),0) | H11: =IFERROR(1000*(1+0.045)/(0.11-0.045),0) | I11: =IFERROR(1000*(1+0.05)/(0.11-0.05),0)
B12: 0.12 | C12: =IFERROR(1000*(1+0.02)/(0.12-0.02),0) | D12: =IFERROR(1000*(1+0.025)/(0.12-0.025),0) | E12: =IFERROR(1000*(1+0.03)/(0.12-0.03),0) | F12: =IFERROR(1000*(1+0.035)/(0.12-0.035),0) | G12: =IFERROR(1000*(1+0.04)/(0.12-0.04),0) | H12: =IFERROR(1000*(1+0.045)/(0.12-0.045),0) | I12: =IFERROR(1000*(1+0.05)/(0.12-0.05),0)
B13: 0.13 | C13: =IFERROR(1000*(1+0.02)/(0.13-0.02),0) | D13: =IFERROR(1000*(1+0.025)/(0.13-0.025),0) | E13: =IFERROR(1000*(1+0.03)/(0.13-0.03),0) | F13: =IFERROR(1000*(1+0.035)/(0.13-0.035),0) | G13: =IFERROR(1000*(1+0.04)/(0.13-0.04),0) | H13: =IFERROR(1000*(1+0.045)/(0.13-0.045),0) | I13: =IFERROR(1000*(1+0.05)/(0.13-0.05),0)
B14: 0.14 | C14: =IFERROR(1000*(1+0.02)/(0.14-0.02),0) | D14: =IFERROR(1000*(1+0.025)/(0.14-0.025),0) | E14: =IFERROR(1000*(1+0.03)/(0.14-0.03),0) | F14: =IFERROR(1000*(1+0.035)/(0.14-0.035),0) | G14: =IFERROR(1000*(1+0.04)/(0.14-0.04),0) | H14: =IFERROR(1000*(1+0.045)/(0.14-0.045),0) | I14: =IFERROR(1000*(1+0.05)/(0.14-0.05),0)
B18: Revenue Growth vs EBITDA Margin Impact on EV
B20: Growth \ Margin | C20: 0.15 | D20: 0.2 | E20: 0.25 | F20: 0.3 | G20: 0.35
B21: 0.05 | C21: =10000*((1+0.05)^5)*0.15*8 | D21: =10000*((1+0.05)^5)*0.2*8 | E21: =10000*((1+0.05)^5)*0.25*8 | F21: =10000*((1+0.05)^5)*0.3*8 | G21: =10000*((1+0.05)^5)*0.35*8
B22: 0.08 | C22: =10000*((1+0.08)^5)*0.15*8 | D22: =10000*((1+0.08)^5)*0.2*8 | E22: =10000*((1+0.08)^5)*0.25*8 | F22: =10000*((1+0.08)^5)*0.3*8 | G22: =10000*((1+0.08)^5)*0.35*8
B23: 0.1 | C23: =10000*((1+0.1)^5)*0.15*8 | D23: =10000*((1+0.1)^5)*0.2*8 | E23: =10000*((1+0.1)^5)*0.25*8 | F23: =10000*((1+0.1)^5)*0.3*8 | G23: =10000*((1+0.1)^5)*0.35*8
B24: 0.12 | C24: =10000*((1+0.12)^5)*0.15*8 | D24: =10000*((1+0.12)^5)*0.2*8 | E24: =10000*((1+0.12)^5)*0.25*8 | F24: =10000*((1+0.12)^5)*0.3*8 | G24: =10000*((1+0.12)^5)*0.35*8
B25: 0.15 | C25: =10000*((1+0.15)^5)*0.15*8 | D25: =10000*((1+0.15)^5)*0.2*8 | E25: =10000*((1+0.15)^5)*0.25*8 | F25: =10000*((1+0.15)^5)*0.3*8 | G25: =10000*((1+0.15)^5)*0.35*8
B26: 0.18 | C26: =10000*((1+0.18)^5)*0.15*8 | D26: =10000*((1+0.18)^5)*0.2*8 | E26: =10000*((1+0.18)^5)*0.25*8 | F26: =10000*((1+0.18)^5)*0.3*8 | G26: =10000*((1+0.18)^5)*0.35*8
B27: 0.2 | C27: =10000*((1+0.2)^5)*0.15*8 | D27: =10000*((1+0.2)^5)*0.2*8 | E27: =10000*((1+0.2)^5)*0.25*8 | F27: =10000*((1+0.2)^5)*0.3*8 | G27: =10000*((1+0.2)^5)*0.35*8

Sheet Scenarios
B2: Scenario Analysis
B5: Scenario | C5: Bear | D5: Base | E5: Bull
B6: Revenue Growth | C6: 0.05 | D6: 0.1 | E6: 0.15
B7: EBITDA Margin | C7: 0.18 | D7: 0.25 | E7: 0.32
B8: Terminal Growth | C8: 0.02 | D8: 0.04 | E8: 0.05
B9: WACC | C9: 0.14 | D9: 0.11 | E9: 0.09
B11: ASSUMPTIONS
B12: Capex % Rev | C12: 0.08 | D12: 0.05 | E12: 0.04
B13: Working Capital Days | C13: 60 | D13: 45 | E13: 35
B14: D/E Ratio | C14: 0.8 | D14: 0.5 | E14: 0.3
B15: Tax Rate | C15: 0.3 | D15: 0.25 | E15: 0.22
B17: OUTPUTS
B18: 5Y Revenue CAGR | C18: =C6 | D18: =D6 | E18: =E6
B19: Exit EBITDA | C19: =10000*(1+C6)^5*C7 | D19: =10000*(1+D6)^5*D7 | E19: =10000*(1+E6)^5*E7
B20: Enterprise Value | C20: =C19*6 | D20: =D19*8 | E20: =E19*10
B21: Equity Value | C21: =C20-3000 | D21: =D20-2500 | E21: =E20-2000
B22: Implied Share Price | C22: =C21/10 | D22: =D21/10 | E22: =E21/10
B24: IRR Analysis
B25: Entry Price | C25: 500 | D25: 500 | E25: 500
B26: Exit Price | C26: =C22 | D26: =D22 | E26: =E22
B27: 5Y Return | C27: =(C25/C24)^0.2-1 | D27: =(D25/D24)^0.2-1 | E27: =(E25/E24)^0.2-1

Sheet Dashboard
B2: HDFCBANK - Financial Dashboard
B22: KEY METRICS SUMMARY
B23: Current Revenue | C23: =Income_Statement!G6
B24: Forecast Y5 Revenue | C24: =Income_Statement!L6
B25: Revenue CAGR | C25: =IFERROR((Income_Statement!L6/Income_Statement!G6)^(1/5)-1,0)
B26: Current EBITDA Margin | C26: =G45
B27: Forecast Y5 EBITDA Margin | C27: =L45
B28: Enterprise Value | C28: =Valuation!C44
B29: Equity Value | C29: =Valuation!C46
B30: Implied Share Price | C30: =Valuation!C50
B40: Chart Data
B41: Year | C41: FY2021 | D41: FY2022 | E41: FY2023 | F41: FY2024 | G41: FY2025 | H41: FY2026 | I41: FY2027 | J41: FY2028 | K41: FY2029 | L41: FY2030
B42: Revenue | C42: =Income_Statement!C6 | D42: =Income_Statement!D6 | E42: =Income_Statement!E6 | F42: =Income_Statement!F6 | G42: =Income_Statement!G6 | H42: =Income_Statement!H6 | I42: =Income_Statement!I6 | J42: =Income_Statement!J6 | ... L42: =Income_Statement!L6
B43: EBITDA | C43: =Income_Statement!C15 | D43: =Income_Statement!D15 | E43: =Income_Statement!E15 | F43: =Income_Statement!F15 | G43: =Income_Statement!G15 | H43: =Income_Statement!H15 | I43: =Income_Statement!I15 | J43: =Income_Statement!J15 | ... L43: =Income_Statement!L15
B44: Net Income | C44: =Income_Statement!C26 | D44: =Income_Statement!D26 | E44: =Income_Statement!E26 | F44: =Income_Statement!F26 | G44: =Income_Statement!G26 | H44: =Income_Statement!H26 | I44: =Income_Statement!I26 | J44: =Income_Statement!J26 | ... L44: =Income_Statement!L26
B45: EBITDA Margin % | C45: =IFERROR(C43/C42,0) | D45: =IFERROR(D43/D42,0) | E45: =IFERROR(E43/E42,0) | F45: =IFERROR(F43/F42,0) | G45: =IFERROR(G43/G42,0) | H45: =IFERROR(H43/H42,0) | I45: =IFERROR(I43/I42,0) | J45: =IFERROR(J43/J42,0) | ... L45: =IFERROR(L43/L42,0)
